kuid/__init__.py
kuid-0.2.1.dist-info/LICENSE
kuid-0.2.1.dist-info/METADATA
kuid-0.2.1.dist-info/WHEEL
kuid-0.2.1.dist-info/RECORD
