Metadata-Version: 2.1
Name: kuid
Version: 0.2.1
Summary: Library to shorten UUIDs
License: MIT
Author: Björn Boschman
Author-email: bjorn.boschman@adm.doctor
Requires-Python: >=3.9,<4.0
Classifier: License :: OSI Approved :: MIT License
Classifier: Programming Language :: Python :: 3
Classifier: Programming Language :: Python :: 3.9
Classifier: Programming Language :: Python :: 3.10
Classifier: Programming Language :: Python :: 3.11
Classifier: Programming Language :: Python :: 3.12
Requires-Dist: pybase62
